neko/__init__.py
neko/colorstr.py
neko/esl.py
neko/mysql.py
neko/procbar.py
neko/redisCluterBee.py
neko/ssh.py
neko/tcpdump.py
pyNeko-3.1.dist-info/DESCRIPTION.rst
pyNeko-3.1.dist-info/METADATA
pyNeko-3.1.dist-info/RECORD
pyNeko-3.1.dist-info/WHEEL
pyNeko-3.1.dist-info/metadata.json
pyNeko-3.1.dist-info/top_level.txt
tests/__init__.py
tests/neko_test.py
